{
    "sourceFile": "process/masterdepartment.php",
    "activeCommit": 0,
    "commits": [
        {
            "activePatchIndex": 37,
            "patches": [
                {
                    "date": 1629820726809,
                    "content": "Index: \n===================================================================\n--- \n+++ \n"
                },
                {
                    "date": 1629861938418,
                    "content": "Index: \n===================================================================\n--- \n+++ \n@@ -0,0 +1,127 @@\n+<?php\r\n+require '../connection.php';\r\n+$tipe = $_POST['tipe'];\r\n+if($tipe == \"load\")\r\n+{\r\n+\r\n+    $where_like = [\r\n+        'divisi',\r\n+        'department',\r\n+        'description',\r\n+        'status'\r\n+        \r\n+    ];\r\n+    \r\n+    $response = $_REQUEST;\r\n+    $start    = $response['start'];\r\n+    $length   = $response['length'];\r\n+    $order    = $where_like[$response['order'][0]['column']];\r\n+    $dir      = $response['order'][0]['dir'];\r\n+    $search   = $response['search']['value'];\r\n+    \r\n+    $total_data = mysqli_query($conn, \"select * from department inner join divisi on divisi.id = department.iddivisi\");\r\n+    \r\n+    if(empty($search)) {\r\n+        $query_data = mysqli_query($conn, \"select *, ks.description as subgroupdesc, ks.id as idsubgroup, ks.status as statussubgroup from kategori_subgroup ks inner join kategori_asset ka on ka.id = ks.idkategoriaset ORDER BY $order $dir LIMIT $start, $length\");\r\n+    \r\n+        $total_filtered = mysqli_query($conn, \"select *, ks.description as subgroupdesc, ks.id as idsubgroup, ks.status as statussubgroup from kategori_subgroup ks inner join kategori_asset ka on ka.id = ks.idkategoriaset\");\r\n+    } else {\r\n+        $query_data = mysqli_query($conn, \"select *, ks.description as subgroupdesc, ks.id as idsubgroup, ks.status as statussubgroup from kategori_subgroup ks inner join kategori_asset ka on ka.id = ks.idkategoriaset WHERE ka.nama LIKE '%$search%' OR ks.subgroup LIKE '%$search%' OR ks.description LIKE '%$search%' ORDER BY $order $dir LIMIT $start, $length\");\r\n+    \r\n+        $total_filtered = mysqli_query($conn, \"select *, ks.description as subgroupdesc, ks.id as idsubgroup, ks.status as statussubgroup from kategori_subgroup ks inner join kategori_asset ka on ka.id = ks.idkategoriaset WHERE ka.nama LIKE '%$search%' OR ks.subgroup LIKE '%$search%' OR ks.description LIKE '%$search%'\");\r\n+    }\r\n+    \r\n+    $response['data'] = [];\r\n+    \r\n+    if($query_data) {\r\n+        while($row = mysqli_fetch_assoc($query_data)) {\r\n+            $mystats = \"\";\r\n+            if($row['statussubgroup'] == \"Active\")\r\n+            {\r\n+                $myactionsetto = \"InActive\";\r\n+                $mystats = '<span class=\"badge badge-success\">Active</span>';\r\n+                $myaction = \"<a class='dropdown-item' onclick = setstatus('\".$row['idsubgroup'].\"-\".$myactionsetto.\"')><i class='icon-check'></i>\r\n+                Set InActive</a>'\";\r\n+            }\r\n+            else\r\n+            {\r\n+                $myactionsetto = \"Active\";\r\n+                $mystats = '<span class=\"badge badge-danger\">InActive</span>';\r\n+                $myaction = \"<a class='dropdown-item' onclick = setstatus('\".$row['idsubgroup'].\"-\".$myactionsetto.\"')><i class='icon-check'></i>\r\n+                Set Active</a>'\";\r\n+            }\r\n+            \r\n+            $response['data'][] = [\r\n+                \"<label id ='nama\".$row['idsubgroup'].\"'>\".$row['nama'].\"</label>\",\r\n+                \"<label id ='subgroup\".$row['idsubgroup'].\"'>\".$row['subgroup'].\"</label>\",\r\n+                \"<label id ='description\".$row['idsubgroup'].\"'>\".$row['subgroupdesc'].\"</label>\",\r\n+                \"<label id ='status\".$row['idsubgroup'].\"'>\".$mystats.\"</label>\",\r\n+                ' <div class=\"list-icons\">\r\n+                <div class=\"dropdown\">\r\n+                    <a href=\"#\" class=\"list-icons-item\" data-toggle=\"dropdown\">\r\n+                        <i class=\"icon-menu9\"></i>\r\n+                    </a>\r\n+    \r\n+                    <div class=\"dropdown-menu dropdown-menu-right\">\r\n+                        <a href=\"#myModaledit\" data-toggle=\"modal\" class=\"dropdown-item\" id =\"click-'.$row['idsubgroup'].'\"  onclick = \"openmodaledit(this)\"><i class=\"icon-check\"></i>\r\n+                            Edit</a>\r\n+                        \r\n+                        '.$myaction.'\r\n+                   \r\n+                    </div>\r\n+                </div>\r\n+            </div>'\r\n+            ];\r\n+        }\r\n+    }\r\n+    \r\n+    $response['recordsTotal'] = 0;\r\n+    if($total_data <> FALSE) {\r\n+        $response['recordsTotal'] = mysqli_num_rows($total_data);\r\n+    }\r\n+    \r\n+    $response['recordsFiltered'] = 0;\r\n+    if($total_filtered <> FALSE) {\r\n+        $response['recordsFiltered'] = mysqli_num_rows($total_filtered);\r\n+    }  \r\n+    \r\n+    echo json_encode($response);\r\n+}\r\n+else if($tipe == \"add\"){\r\n+    $group = $_POST['mygroup'];\r\n+    $description = $_POST['descrip'];\r\n+    $subgroup = $_POST['mysubgroup'];\r\n+    $sql = \"INSERT into kategori_subgroup values(NULL, '\".$group.\"', '\".$subgroup.\"', '\".$description.\"' , 'Active')\";\r\n+    $res = $conn->query($sql);\r\n+    if(($conn -> affected_rows)>0)\r\n+    {\r\n+        echo \"sukses\";\r\n+    }\r\n+    else{\r\n+        echo \"tidak\";\r\n+    }\r\n+}\r\n+else if($tipe == \"change\")\r\n+{\r\n+    $id  = $_POST['idchange'];\r\n+    $group = $_POST['mygroup'];\r\n+    $description = $_POST['descrip'];\r\n+    $mysubgroup = $_POST['mysubgroup'];\r\n+    $sql = \"update kategori_subgroup set idkategoriaset = '\".$group.\"', subgroup = '\".$mysubgroup.\"', description = '\".$description.\"' where id = '\".$id.\"'\";\r\n+    $res = $conn->query($sql);\r\n+    if(($conn -> affected_rows)>0)\r\n+    {\r\n+        echo \"sukses\";\r\n+    }\r\n+    else{\r\n+        echo \"tidak\";\r\n+    }\r\n+}\r\n+else if($tipe == \"setstatus\")\r\n+{\r\n+    $myid = $_POST['myidchange'];\r\n+    $stat = $_POST['stat'];\r\n+    $sql = \"update kategori_subgroup set status = '\".$stat.\"' where id = '\".$myid.\"'\";\r\n+    $res = $conn->query($sql);\r\n+}\r\n+?>\n\\ No newline at end of file\n"
                },
                {
                    "date": 1629861952576,
                    "content": "Index: \n===================================================================\n--- \n+++ \n@@ -18,9 +18,9 @@\n     $order    = $where_like[$response['order'][0]['column']];\r\n     $dir      = $response['order'][0]['dir'];\r\n     $search   = $response['search']['value'];\r\n     \r\n-    $total_data = mysqli_query($conn, \"select * from department inner join divisi on divisi.id = department.iddivisi\");\r\n+    $total_data = mysqli_query($conn, \"select *, department.description as depardesc from department inner join divisi on divisi.id = department.iddivisi\");\r\n     \r\n     if(empty($search)) {\r\n         $query_data = mysqli_query($conn, \"select *, ks.description as subgroupdesc, ks.id as idsubgroup, ks.status as statussubgroup from kategori_subgroup ks inner join kategori_asset ka on ka.id = ks.idkategoriaset ORDER BY $order $dir LIMIT $start, $length\");\r\n     \r\n"
                },
                {
                    "date": 1629861964776,
                    "content": "Index: \n===================================================================\n--- \n+++ \n@@ -21,9 +21,9 @@\n     \r\n     $total_data = mysqli_query($conn, \"select *, department.description as depardesc from department inner join divisi on divisi.id = department.iddivisi\");\r\n     \r\n     if(empty($search)) {\r\n-        $query_data = mysqli_query($conn, \"select *, ks.description as subgroupdesc, ks.id as idsubgroup, ks.status as statussubgroup from kategori_subgroup ks inner join kategori_asset ka on ka.id = ks.idkategoriaset ORDER BY $order $dir LIMIT $start, $length\");\r\n+        $query_data = mysqli_query($conn, \"select *, department.description as depardesc from department inner join divisi on divisi.id = department.iddivisi ORDER BY $order $dir LIMIT $start, $length\");\r\n     \r\n         $total_filtered = mysqli_query($conn, \"select *, ks.description as subgroupdesc, ks.id as idsubgroup, ks.status as statussubgroup from kategori_subgroup ks inner join kategori_asset ka on ka.id = ks.idkategoriaset\");\r\n     } else {\r\n         $query_data = mysqli_query($conn, \"select *, ks.description as subgroupdesc, ks.id as idsubgroup, ks.status as statussubgroup from kategori_subgroup ks inner join kategori_asset ka on ka.id = ks.idkategoriaset WHERE ka.nama LIKE '%$search%' OR ks.subgroup LIKE '%$search%' OR ks.description LIKE '%$search%' ORDER BY $order $dir LIMIT $start, $length\");\r\n"
                },
                {
                    "date": 1629861971900,
                    "content": "Index: \n===================================================================\n--- \n+++ \n@@ -23,9 +23,9 @@\n     \r\n     if(empty($search)) {\r\n         $query_data = mysqli_query($conn, \"select *, department.description as depardesc from department inner join divisi on divisi.id = department.iddivisi ORDER BY $order $dir LIMIT $start, $length\");\r\n     \r\n-        $total_filtered = mysqli_query($conn, \"select *, ks.description as subgroupdesc, ks.id as idsubgroup, ks.status as statussubgroup from kategori_subgroup ks inner join kategori_asset ka on ka.id = ks.idkategoriaset\");\r\n+        $total_filtered = mysqli_query($conn, \"select *, department.description as depardesc from department inner join divisi on divisi.id = department.iddivisi\");\r\n     } else {\r\n         $query_data = mysqli_query($conn, \"select *, ks.description as subgroupdesc, ks.id as idsubgroup, ks.status as statussubgroup from kategori_subgroup ks inner join kategori_asset ka on ka.id = ks.idkategoriaset WHERE ka.nama LIKE '%$search%' OR ks.subgroup LIKE '%$search%' OR ks.description LIKE '%$search%' ORDER BY $order $dir LIMIT $start, $length\");\r\n     \r\n         $total_filtered = mysqli_query($conn, \"select *, ks.description as subgroupdesc, ks.id as idsubgroup, ks.status as statussubgroup from kategori_subgroup ks inner join kategori_asset ka on ka.id = ks.idkategoriaset WHERE ka.nama LIKE '%$search%' OR ks.subgroup LIKE '%$search%' OR ks.description LIKE '%$search%'\");\r\n"
                },
                {
                    "date": 1629861979524,
                    "content": "Index: \n===================================================================\n--- \n+++ \n@@ -25,9 +25,9 @@\n         $query_data = mysqli_query($conn, \"select *, department.description as depardesc from department inner join divisi on divisi.id = department.iddivisi ORDER BY $order $dir LIMIT $start, $length\");\r\n     \r\n         $total_filtered = mysqli_query($conn, \"select *, department.description as depardesc from department inner join divisi on divisi.id = department.iddivisi\");\r\n     } else {\r\n-        $query_data = mysqli_query($conn, \"select *, ks.description as subgroupdesc, ks.id as idsubgroup, ks.status as statussubgroup from kategori_subgroup ks inner join kategori_asset ka on ka.id = ks.idkategoriaset WHERE ka.nama LIKE '%$search%' OR ks.subgroup LIKE '%$search%' OR ks.description LIKE '%$search%' ORDER BY $order $dir LIMIT $start, $length\");\r\n+        $query_data = mysqli_query($conn, \"select *, department.description as depardesc from department inner join divisi on divisi.id = department.iddivisi WHERE ka.nama LIKE '%$search%' OR ks.subgroup LIKE '%$search%' OR ks.description LIKE '%$search%' ORDER BY $order $dir LIMIT $start, $length\");\r\n     \r\n         $total_filtered = mysqli_query($conn, \"select *, ks.description as subgroupdesc, ks.id as idsubgroup, ks.status as statussubgroup from kategori_subgroup ks inner join kategori_asset ka on ka.id = ks.idkategoriaset WHERE ka.nama LIKE '%$search%' OR ks.subgroup LIKE '%$search%' OR ks.description LIKE '%$search%'\");\r\n     }\r\n     \r\n"
                },
                {
                    "date": 1629862039519,
                    "content": "Index: \n===================================================================\n--- \n+++ \n@@ -25,9 +25,9 @@\n         $query_data = mysqli_query($conn, \"select *, department.description as depardesc from department inner join divisi on divisi.id = department.iddivisi ORDER BY $order $dir LIMIT $start, $length\");\r\n     \r\n         $total_filtered = mysqli_query($conn, \"select *, department.description as depardesc from department inner join divisi on divisi.id = department.iddivisi\");\r\n     } else {\r\n-        $query_data = mysqli_query($conn, \"select *, department.description as depardesc from department inner join divisi on divisi.id = department.iddivisi WHERE ka.nama LIKE '%$search%' OR ks.subgroup LIKE '%$search%' OR ks.description LIKE '%$search%' ORDER BY $order $dir LIMIT $start, $length\");\r\n+        $query_data = mysqli_query($conn, \"select *, department.description as depardesc from department inner join divisi on divisi.id = department.iddivisi WHERE divisi.divisi LIKE '%$search%' OR department.description LIKE '%$search%' OR department.department LIKE '%$search%' OR department.status LIKE '%$search%' ORDER BY $order $dir LIMIT $start, $length\");\r\n     \r\n         $total_filtered = mysqli_query($conn, \"select *, ks.description as subgroupdesc, ks.id as idsubgroup, ks.status as statussubgroup from kategori_subgroup ks inner join kategori_asset ka on ka.id = ks.idkategoriaset WHERE ka.nama LIKE '%$search%' OR ks.subgroup LIKE '%$search%' OR ks.description LIKE '%$search%'\");\r\n     }\r\n     \r\n"
                },
                {
                    "date": 1629862057144,
                    "content": "Index: \n===================================================================\n--- \n+++ \n@@ -27,9 +27,9 @@\n         $total_filtered = mysqli_query($conn, \"select *, department.description as depardesc from department inner join divisi on divisi.id = department.iddivisi\");\r\n     } else {\r\n         $query_data = mysqli_query($conn, \"select *, department.description as depardesc from department inner join divisi on divisi.id = department.iddivisi WHERE divisi.divisi LIKE '%$search%' OR department.description LIKE '%$search%' OR department.department LIKE '%$search%' OR department.status LIKE '%$search%' ORDER BY $order $dir LIMIT $start, $length\");\r\n     \r\n-        $total_filtered = mysqli_query($conn, \"select *, ks.description as subgroupdesc, ks.id as idsubgroup, ks.status as statussubgroup from kategori_subgroup ks inner join kategori_asset ka on ka.id = ks.idkategoriaset WHERE ka.nama LIKE '%$search%' OR ks.subgroup LIKE '%$search%' OR ks.description LIKE '%$search%'\");\r\n+        $total_filtered = mysqli_query($conn, \"select *, department.description as depardesc from department inner join divisi on divisi.id = department.iddivisi WHERE divisi.divisi LIKE '%$search%' OR department.description LIKE '%$search%' OR department.department LIKE '%$search%' OR department.status LIKE '%$search%'\");\r\n     }\r\n     \r\n     $response['data'] = [];\r\n     \r\n"
                },
                {
                    "date": 1629862082737,
                    "content": "Index: \n===================================================================\n--- \n+++ \n@@ -18,9 +18,9 @@\n     $order    = $where_like[$response['order'][0]['column']];\r\n     $dir      = $response['order'][0]['dir'];\r\n     $search   = $response['search']['value'];\r\n     \r\n-    $total_data = mysqli_query($conn, \"select *, department.description as depardesc from department inner join divisi on divisi.id = department.iddivisi\");\r\n+    $total_data = mysqli_query($conn, \"select *, department.description as depardesc, department.id as iddepartment from department inner join divisi on divisi.id = department.iddivisi\");\r\n     \r\n     if(empty($search)) {\r\n         $query_data = mysqli_query($conn, \"select *, department.description as depardesc from department inner join divisi on divisi.id = department.iddivisi ORDER BY $order $dir LIMIT $start, $length\");\r\n     \r\n"
                },
                {
                    "date": 1629862096513,
                    "content": "Index: \n===================================================================\n--- \n+++ \n@@ -21,15 +21,15 @@\n     \r\n     $total_data = mysqli_query($conn, \"select *, department.description as depardesc, department.id as iddepartment from department inner join divisi on divisi.id = department.iddivisi\");\r\n     \r\n     if(empty($search)) {\r\n-        $query_data = mysqli_query($conn, \"select *, department.description as depardesc from department inner join divisi on divisi.id = department.iddivisi ORDER BY $order $dir LIMIT $start, $length\");\r\n+        $query_data = mysqli_query($conn, \"select *, department.description as depardesc , department.id as iddepartment from department inner join divisi on divisi.id = department.iddivisi ORDER BY $order $dir LIMIT $start, $length\");\r\n     \r\n-        $total_filtered = mysqli_query($conn, \"select *, department.description as depardesc from department inner join divisi on divisi.id = department.iddivisi\");\r\n+        $total_filtered = mysqli_query($conn, \"select *, department.description as depardesc , department.id as iddepartment  from department inner join divisi on divisi.id = department.iddivisi\");\r\n     } else {\r\n-        $query_data = mysqli_query($conn, \"select *, department.description as depardesc from department inner join divisi on divisi.id = department.iddivisi WHERE divisi.divisi LIKE '%$search%' OR department.description LIKE '%$search%' OR department.department LIKE '%$search%' OR department.status LIKE '%$search%' ORDER BY $order $dir LIMIT $start, $length\");\r\n+        $query_data = mysqli_query($conn, \"select *, department.description as depardesc , department.id as iddepartment from department inner join divisi on divisi.id = department.iddivisi WHERE divisi.divisi LIKE '%$search%' OR department.description LIKE '%$search%' OR department.department LIKE '%$search%' OR department.status LIKE '%$search%' ORDER BY $order $dir LIMIT $start, $length\");\r\n     \r\n-        $total_filtered = mysqli_query($conn, \"select *, department.description as depardesc from department inner join divisi on divisi.id = department.iddivisi WHERE divisi.divisi LIKE '%$search%' OR department.description LIKE '%$search%' OR department.department LIKE '%$search%' OR department.status LIKE '%$search%'\");\r\n+        $total_filtered = mysqli_query($conn, \"select *, department.description as depardesc , department.id as iddepartment from department inner join divisi on divisi.id = department.iddivisi WHERE divisi.divisi LIKE '%$search%' OR department.description LIKE '%$search%' OR department.department LIKE '%$search%' OR department.status LIKE '%$search%'\");\r\n     }\r\n     \r\n     $response['data'] = [];\r\n     \r\n"
                },
                {
                    "date": 1629862103925,
                    "content": "Index: \n===================================================================\n--- \n+++ \n@@ -51,20 +51,20 @@\n                 Set Active</a>'\";\r\n             }\r\n             \r\n             $response['data'][] = [\r\n-                \"<label id ='nama\".$row['idsubgroup'].\"'>\".$row['nama'].\"</label>\",\r\n-                \"<label id ='subgroup\".$row['idsubgroup'].\"'>\".$row['subgroup'].\"</label>\",\r\n-                \"<label id ='description\".$row['idsubgroup'].\"'>\".$row['subgroupdesc'].\"</label>\",\r\n-                \"<label id ='status\".$row['idsubgroup'].\"'>\".$mystats.\"</label>\",\r\n+                \"<label id ='nama\".$row['iddepartment'].\"'>\".$row['nama'].\"</label>\",\r\n+                \"<label id ='subgroup\".$row['iddepartment'].\"'>\".$row['subgroup'].\"</label>\",\r\n+                \"<label id ='description\".$row['iddepartment'].\"'>\".$row['subgroupdesc'].\"</label>\",\r\n+                \"<label id ='status\".$row['iddepartment'].\"'>\".$mystats.\"</label>\",\r\n                 ' <div class=\"list-icons\">\r\n                 <div class=\"dropdown\">\r\n                     <a href=\"#\" class=\"list-icons-item\" data-toggle=\"dropdown\">\r\n                         <i class=\"icon-menu9\"></i>\r\n                     </a>\r\n     \r\n                     <div class=\"dropdown-menu dropdown-menu-right\">\r\n-                        <a href=\"#myModaledit\" data-toggle=\"modal\" class=\"dropdown-item\" id =\"click-'.$row['idsubgroup'].'\"  onclick = \"openmodaledit(this)\"><i class=\"icon-check\"></i>\r\n+                        <a href=\"#myModaledit\" data-toggle=\"modal\" class=\"dropdown-item\" id =\"click-'.$row['iddepartment'].'\"  onclick = \"openmodaledit(this)\"><i class=\"icon-check\"></i>\r\n                             Edit</a>\r\n                         \r\n                         '.$myaction.'\r\n                    \r\n"
                },
                {
                    "date": 1629862114829,
                    "content": "Index: \n===================================================================\n--- \n+++ \n@@ -39,21 +39,21 @@\n             if($row['statussubgroup'] == \"Active\")\r\n             {\r\n                 $myactionsetto = \"InActive\";\r\n                 $mystats = '<span class=\"badge badge-success\">Active</span>';\r\n-                $myaction = \"<a class='dropdown-item' onclick = setstatus('\".$row['idsubgroup'].\"-\".$myactionsetto.\"')><i class='icon-check'></i>\r\n+                $myaction = \"<a class='dropdown-item' onclick = setstatus('\".$row['iddepartment'].\"-\".$myactionsetto.\"')><i class='icon-check'></i>\r\n                 Set InActive</a>'\";\r\n             }\r\n             else\r\n             {\r\n                 $myactionsetto = \"Active\";\r\n                 $mystats = '<span class=\"badge badge-danger\">InActive</span>';\r\n-                $myaction = \"<a class='dropdown-item' onclick = setstatus('\".$row['idsubgroup'].\"-\".$myactionsetto.\"')><i class='icon-check'></i>\r\n+                $myaction = \"<a class='dropdown-item' onclick = setstatus('\".$row['iddepartment'].\"-\".$myactionsetto.\"')><i class='icon-check'></i>\r\n                 Set Active</a>'\";\r\n             }\r\n             \r\n             $response['data'][] = [\r\n-                \"<label id ='nama\".$row['iddepartment'].\"'>\".$row['nama'].\"</label>\",\r\n+                \"<label id ='divisi\".$row['iddepartment'].\"'>\".$row['nama'].\"</label>\",\r\n                 \"<label id ='subgroup\".$row['iddepartment'].\"'>\".$row['subgroup'].\"</label>\",\r\n                 \"<label id ='description\".$row['iddepartment'].\"'>\".$row['subgroupdesc'].\"</label>\",\r\n                 \"<label id ='status\".$row['iddepartment'].\"'>\".$mystats.\"</label>\",\r\n                 ' <div class=\"list-icons\">\r\n"
                },
                {
                    "date": 1629862149732,
                    "content": "Index: \n===================================================================\n--- \n+++ \n@@ -52,9 +52,9 @@\n             }\r\n             \r\n             $response['data'][] = [\r\n                 \"<label id ='divisi\".$row['iddepartment'].\"'>\".$row['nama'].\"</label>\",\r\n-                \"<label id ='subgroup\".$row['iddepartment'].\"'>\".$row['subgroup'].\"</label>\",\r\n+                \"<label id ='department\".$row['iddepartment'].\"'>\".$row['subgroup'].\"</label>\",\r\n                 \"<label id ='description\".$row['iddepartment'].\"'>\".$row['subgroupdesc'].\"</label>\",\r\n                 \"<label id ='status\".$row['iddepartment'].\"'>\".$mystats.\"</label>\",\r\n                 ' <div class=\"list-icons\">\r\n                 <div class=\"dropdown\">\r\n"
                },
                {
                    "date": 1629862170238,
                    "content": "Index: \n===================================================================\n--- \n+++ \n@@ -51,9 +51,9 @@\n                 Set Active</a>'\";\r\n             }\r\n             \r\n             $response['data'][] = [\r\n-                \"<label id ='divisi\".$row['iddepartment'].\"'>\".$row['nama'].\"</label>\",\r\n+                \"<label id ='divisi\".$row['iddepartment'].\"'>\".$row['divisi'].\"</label>\",\r\n                 \"<label id ='department\".$row['iddepartment'].\"'>\".$row['subgroup'].\"</label>\",\r\n                 \"<label id ='description\".$row['iddepartment'].\"'>\".$row['subgroupdesc'].\"</label>\",\r\n                 \"<label id ='status\".$row['iddepartment'].\"'>\".$mystats.\"</label>\",\r\n                 ' <div class=\"list-icons\">\r\n"
                },
                {
                    "date": 1629862180181,
                    "content": "Index: \n===================================================================\n--- \n+++ \n@@ -52,10 +52,10 @@\n             }\r\n             \r\n             $response['data'][] = [\r\n                 \"<label id ='divisi\".$row['iddepartment'].\"'>\".$row['divisi'].\"</label>\",\r\n-                \"<label id ='department\".$row['iddepartment'].\"'>\".$row['subgroup'].\"</label>\",\r\n-                \"<label id ='description\".$row['iddepartment'].\"'>\".$row['subgroupdesc'].\"</label>\",\r\n+                \"<label id ='department\".$row['iddepartment'].\"'>\".$row['department'].\"</label>\",\r\n+                \"<label id ='description\".$row['iddepartment'].\"'>\".$row['depardesc'].\"</label>\",\r\n                 \"<label id ='status\".$row['iddepartment'].\"'>\".$mystats.\"</label>\",\r\n                 ' <div class=\"list-icons\">\r\n                 <div class=\"dropdown\">\r\n                     <a href=\"#\" class=\"list-icons-item\" data-toggle=\"dropdown\">\r\n"
                },
                {
                    "date": 1629862209260,
                    "content": "Index: \n===================================================================\n--- \n+++ \n@@ -18,18 +18,18 @@\n     $order    = $where_like[$response['order'][0]['column']];\r\n     $dir      = $response['order'][0]['dir'];\r\n     $search   = $response['search']['value'];\r\n     \r\n-    $total_data = mysqli_query($conn, \"select *, department.description as depardesc, department.id as iddepartment from department inner join divisi on divisi.id = department.iddivisi\");\r\n+    $total_data = mysqli_query($conn, \"select *, department.description as depardesc, department.id as iddepartment, department.status as statdepartment from department inner join divisi on divisi.id = department.iddivisi\");\r\n     \r\n     if(empty($search)) {\r\n-        $query_data = mysqli_query($conn, \"select *, department.description as depardesc , department.id as iddepartment from department inner join divisi on divisi.id = department.iddivisi ORDER BY $order $dir LIMIT $start, $length\");\r\n+        $query_data = mysqli_query($conn, \"select *, department.description as depardesc , department.id as iddepartment, department.status as statdepartment from department inner join divisi on divisi.id = department.iddivisi ORDER BY $order $dir LIMIT $start, $length\");\r\n     \r\n-        $total_filtered = mysqli_query($conn, \"select *, department.description as depardesc , department.id as iddepartment  from department inner join divisi on divisi.id = department.iddivisi\");\r\n+        $total_filtered = mysqli_query($conn, \"select *, department.description as depardesc , department.id as iddepartment, department.status as statdepartment  from department inner join divisi on divisi.id = department.iddivisi\");\r\n     } else {\r\n-        $query_data = mysqli_query($conn, \"select *, department.description as depardesc , department.id as iddepartment from department inner join divisi on divisi.id = department.iddivisi WHERE divisi.divisi LIKE '%$search%' OR department.description LIKE '%$search%' OR department.department LIKE '%$search%' OR department.status LIKE '%$search%' ORDER BY $order $dir LIMIT $start, $length\");\r\n+        $query_data = mysqli_query($conn, \"select *, department.description as depardesc , department.id as iddepartment, department.status as statdepartment from department inner join divisi on divisi.id = department.iddivisi WHERE divisi.divisi LIKE '%$search%' OR department.description LIKE '%$search%' OR department.department LIKE '%$search%' OR department.status LIKE '%$search%' ORDER BY $order $dir LIMIT $start, $length\");\r\n     \r\n-        $total_filtered = mysqli_query($conn, \"select *, department.description as depardesc , department.id as iddepartment from department inner join divisi on divisi.id = department.iddivisi WHERE divisi.divisi LIKE '%$search%' OR department.description LIKE '%$search%' OR department.department LIKE '%$search%' OR department.status LIKE '%$search%'\");\r\n+        $total_filtered = mysqli_query($conn, \"select *, department.description as depardesc , department.id as iddepartment, department.status as statdepartment from department inner join divisi on divisi.id = department.iddivisi WHERE divisi.divisi LIKE '%$search%' OR department.description LIKE '%$search%' OR department.department LIKE '%$search%' OR department.status LIKE '%$search%'\");\r\n     }\r\n     \r\n     $response['data'] = [];\r\n     \r\n"
                },
                {
                    "date": 1629862243358,
                    "content": "Index: \n===================================================================\n--- \n+++ \n@@ -35,9 +35,9 @@\n     \r\n     if($query_data) {\r\n         while($row = mysqli_fetch_assoc($query_data)) {\r\n             $mystats = \"\";\r\n-            if($row['statussubgroup'] == \"Active\")\r\n+            if($row['statdepartment'] == \"Active\")\r\n             {\r\n                 $myactionsetto = \"InActive\";\r\n                 $mystats = '<span class=\"badge badge-success\">Active</span>';\r\n                 $myaction = \"<a class='dropdown-item' onclick = setstatus('\".$row['iddepartment'].\"-\".$myactionsetto.\"')><i class='icon-check'></i>\r\n"
                },
                {
                    "date": 1629862504189,
                    "content": "Index: \n===================================================================\n--- \n+++ \n@@ -120,8 +120,8 @@\n else if($tipe == \"setstatus\")\r\n {\r\n     $myid = $_POST['myidchange'];\r\n     $stat = $_POST['stat'];\r\n-    $sql = \"update kategori_subgroup set status = '\".$stat.\"' where id = '\".$myid.\"'\";\r\n+    $sql = \"update department set status = '\".$stat.\"' where id = '\".$myid.\"'\";\r\n     $res = $conn->query($sql);\r\n }\r\n ?>\n\\ No newline at end of file\n"
                },
                {
                    "date": 1629863012203,
                    "content": "Index: \n===================================================================\n--- \n+++ \n@@ -86,9 +86,9 @@\n     }  \r\n     \r\n     echo json_encode($response);\r\n }\r\n-else if($tipe == \"add\"){\r\n+else if($tipe == \"adddepartment\"){\r\n     $group = $_POST['mygroup'];\r\n     $description = $_POST['descrip'];\r\n     $subgroup = $_POST['mysubgroup'];\r\n     $sql = \"INSERT into kategori_subgroup values(NULL, '\".$group.\"', '\".$subgroup.\"', '\".$description.\"' , 'Active')\";\r\n"
                },
                {
                    "date": 1629863053469,
                    "content": "Index: \n===================================================================\n--- \n+++ \n@@ -87,8 +87,11 @@\n     \r\n     echo json_encode($response);\r\n }\r\n else if($tipe == \"adddepartment\"){\r\n+    mydiv : division,\r\n+    mydepar : department,\r\n+    mydesc : desc\r\n     $group = $_POST['mygroup'];\r\n     $description = $_POST['descrip'];\r\n     $subgroup = $_POST['mysubgroup'];\r\n     $sql = \"INSERT into kategori_subgroup values(NULL, '\".$group.\"', '\".$subgroup.\"', '\".$description.\"' , 'Active')\";\r\n"
                },
                {
                    "date": 1629863062649,
                    "content": "Index: \n===================================================================\n--- \n+++ \n@@ -90,11 +90,11 @@\n else if($tipe == \"adddepartment\"){\r\n     mydiv : division,\r\n     mydepar : department,\r\n     mydesc : desc\r\n-    $group = $_POST['mygroup'];\r\n+    $mydiv = $_POST['mydiv'];\r\n     $description = $_POST['descrip'];\r\n-    $subgroup = $_POST['mysubgroup'];\r\n+    $mydepar = $_POST['mydepar'];\r\n     $sql = \"INSERT into kategori_subgroup values(NULL, '\".$group.\"', '\".$subgroup.\"', '\".$description.\"' , 'Active')\";\r\n     $res = $conn->query($sql);\r\n     if(($conn -> affected_rows)>0)\r\n     {\r\n"
                },
                {
                    "date": 1629863070058,
                    "content": "Index: \n===================================================================\n--- \n+++ \n@@ -87,13 +87,11 @@\n     \r\n     echo json_encode($response);\r\n }\r\n else if($tipe == \"adddepartment\"){\r\n-    mydiv : division,\r\n-    mydepar : department,\r\n-    mydesc : desc\r\n+  \r\n     $mydiv = $_POST['mydiv'];\r\n-    $description = $_POST['descrip'];\r\n+    $mydesc = $_POST['mydesc'];\r\n     $mydepar = $_POST['mydepar'];\r\n     $sql = \"INSERT into kategori_subgroup values(NULL, '\".$group.\"', '\".$subgroup.\"', '\".$description.\"' , 'Active')\";\r\n     $res = $conn->query($sql);\r\n     if(($conn -> affected_rows)>0)\r\n"
                },
                {
                    "date": 1629863075146,
                    "content": "Index: \n===================================================================\n--- \n+++ \n@@ -87,13 +87,12 @@\n     \r\n     echo json_encode($response);\r\n }\r\n else if($tipe == \"adddepartment\"){\r\n-  \r\n     $mydiv = $_POST['mydiv'];\r\n     $mydesc = $_POST['mydesc'];\r\n     $mydepar = $_POST['mydepar'];\r\n-    $sql = \"INSERT into kategori_subgroup values(NULL, '\".$group.\"', '\".$subgroup.\"', '\".$description.\"' , 'Active')\";\r\n+    $sql = \"INSERT into departmetn values(NULL, '\".$group.\"', '\".$subgroup.\"', '\".$description.\"' , 'Active')\";\r\n     $res = $conn->query($sql);\r\n     if(($conn -> affected_rows)>0)\r\n     {\r\n         echo \"sukses\";\r\n"
                },
                {
                    "date": 1629863081323,
                    "content": "Index: \n===================================================================\n--- \n+++ \n@@ -90,9 +90,9 @@\n else if($tipe == \"adddepartment\"){\r\n     $mydiv = $_POST['mydiv'];\r\n     $mydesc = $_POST['mydesc'];\r\n     $mydepar = $_POST['mydepar'];\r\n-    $sql = \"INSERT into departmetn values(NULL, '\".$group.\"', '\".$subgroup.\"', '\".$description.\"' , 'Active')\";\r\n+    $sql = \"INSERT into department values(NULL, '\".$mydiv.\"', '\".$subgroup.\"', '\".$description.\"' , 'Active')\";\r\n     $res = $conn->query($sql);\r\n     if(($conn -> affected_rows)>0)\r\n     {\r\n         echo \"sukses\";\r\n"
                },
                {
                    "date": 1629863088510,
                    "content": "Index: \n===================================================================\n--- \n+++ \n@@ -90,9 +90,9 @@\n else if($tipe == \"adddepartment\"){\r\n     $mydiv = $_POST['mydiv'];\r\n     $mydesc = $_POST['mydesc'];\r\n     $mydepar = $_POST['mydepar'];\r\n-    $sql = \"INSERT into department values(NULL, '\".$mydiv.\"', '\".$subgroup.\"', '\".$description.\"' , 'Active')\";\r\n+    $sql = \"INSERT into department values(NULL, '\".$mydiv.\"', '\".$subgroup.\"', '\".$mydesc.\"' , 'Active')\";\r\n     $res = $conn->query($sql);\r\n     if(($conn -> affected_rows)>0)\r\n     {\r\n         echo \"sukses\";\r\n"
                },
                {
                    "date": 1629863625555,
                    "content": "Index: \n===================================================================\n--- \n+++ \n@@ -62,9 +62,9 @@\n                         <i class=\"icon-menu9\"></i>\r\n                     </a>\r\n     \r\n                     <div class=\"dropdown-menu dropdown-menu-right\">\r\n-                        <a href=\"#myModaledit\" data-toggle=\"modal\" class=\"dropdown-item\" id =\"click-'.$row['iddepartment'].'\"  onclick = \"openmodaledit(this)\"><i class=\"icon-check\"></i>\r\n+                        <a href=\"#myModaledit\" data-toggle=\"modal\" class=\"dropdown-item\" id =\"click-'.$row['iddepartment'].'-'..'\"  onclick = \"openmodaledit(this)\"><i class=\"icon-check\"></i>\r\n                             Edit</a>\r\n                         \r\n                         '.$myaction.'\r\n                    \r\n@@ -90,9 +90,9 @@\n else if($tipe == \"adddepartment\"){\r\n     $mydiv = $_POST['mydiv'];\r\n     $mydesc = $_POST['mydesc'];\r\n     $mydepar = $_POST['mydepar'];\r\n-    $sql = \"INSERT into department values(NULL, '\".$mydiv.\"', '\".$subgroup.\"', '\".$mydesc.\"' , 'Active')\";\r\n+    $sql = \"INSERT into department values(NULL, '\".$mydiv.\"', '\".$mydepar.\"', '\".$mydesc.\"' , 'Active')\";\r\n     $res = $conn->query($sql);\r\n     if(($conn -> affected_rows)>0)\r\n     {\r\n         echo \"sukses\";\r\n"
                },
                {
                    "date": 1629863660821,
                    "content": "Index: \n===================================================================\n--- \n+++ \n@@ -62,9 +62,9 @@\n                         <i class=\"icon-menu9\"></i>\r\n                     </a>\r\n     \r\n                     <div class=\"dropdown-menu dropdown-menu-right\">\r\n-                        <a href=\"#myModaledit\" data-toggle=\"modal\" class=\"dropdown-item\" id =\"click-'.$row['iddepartment'].'-'..'\"  onclick = \"openmodaledit(this)\"><i class=\"icon-check\"></i>\r\n+                        <a href=\"#myModaledit\" data-toggle=\"modal\" class=\"dropdown-item\" id =\"click-'.$row['iddepartment'].'-'.$row['iddivisi'].'\"  onclick = \"openmodaledit(this)\"><i class=\"icon-check\"></i>\r\n                             Edit</a>\r\n                         \r\n                         '.$myaction.'\r\n                    \r\n"
                },
                {
                    "date": 1629864092254,
                    "content": "Index: \n===================================================================\n--- \n+++ \n@@ -100,9 +100,9 @@\n     else{\r\n         echo \"tidak\";\r\n     }\r\n }\r\n-else if($tipe == \"change\")\r\n+else if($tipe == \"changedata\")\r\n {\r\n     $id  = $_POST['idchange'];\r\n     $group = $_POST['mygroup'];\r\n     $description = $_POST['descrip'];\r\n"
                },
                {
                    "date": 1629864100977,
                    "content": "Index: \n===================================================================\n--- \n+++ \n@@ -103,9 +103,9 @@\n }\r\n else if($tipe == \"changedata\")\r\n {\r\n     $id  = $_POST['idchange'];\r\n-    $group = $_POST['mygroup'];\r\n+    $group = $_POST['myid'];\r\n     $description = $_POST['descrip'];\r\n     $mysubgroup = $_POST['mysubgroup'];\r\n     $sql = \"update kategori_subgroup set idkategoriaset = '\".$group.\"', subgroup = '\".$mysubgroup.\"', description = '\".$description.\"' where id = '\".$id.\"'\";\r\n     $res = $conn->query($sql);\r\n"
                },
                {
                    "date": 1629864109322,
                    "content": "Index: \n===================================================================\n--- \n+++ \n@@ -104,10 +104,10 @@\n else if($tipe == \"changedata\")\r\n {\r\n     $id  = $_POST['idchange'];\r\n     $group = $_POST['myid'];\r\n-    $description = $_POST['descrip'];\r\n-    $mysubgroup = $_POST['mysubgroup'];\r\n+    $description = $_POST['mydivision'];\r\n+    $mysubgroup = $_POST['mydepar'];\r\n     $sql = \"update kategori_subgroup set idkategoriaset = '\".$group.\"', subgroup = '\".$mysubgroup.\"', description = '\".$description.\"' where id = '\".$id.\"'\";\r\n     $res = $conn->query($sql);\r\n     if(($conn -> affected_rows)>0)\r\n     {\r\n"
                },
                {
                    "date": 1629864121934,
                    "content": "Index: \n===================================================================\n--- \n+++ \n@@ -104,10 +104,12 @@\n else if($tipe == \"changedata\")\r\n {\r\n     $id  = $_POST['idchange'];\r\n     $group = $_POST['myid'];\r\n+    $mysubgroup = $_POST['mydepar'];\r\n+    $mysubgroup = $_POST['mydesc'];\r\n     $description = $_POST['mydivision'];\r\n-    $mysubgroup = $_POST['mydepar'];\r\n+    \r\n     $sql = \"update kategori_subgroup set idkategoriaset = '\".$group.\"', subgroup = '\".$mysubgroup.\"', description = '\".$description.\"' where id = '\".$id.\"'\";\r\n     $res = $conn->query($sql);\r\n     if(($conn -> affected_rows)>0)\r\n     {\r\n"
                },
                {
                    "date": 1629864142892,
                    "content": "Index: \n===================================================================\n--- \n+++ \n@@ -102,9 +102,9 @@\n     }\r\n }\r\n else if($tipe == \"changedata\")\r\n {\r\n-    $id  = $_POST['idchange'];\r\n+    $id  = $_POST['myid'];\r\n     $group = $_POST['myid'];\r\n     $mysubgroup = $_POST['mydepar'];\r\n     $mysubgroup = $_POST['mydesc'];\r\n     $description = $_POST['mydivision'];\r\n"
                },
                {
                    "date": 1629864181440,
                    "content": "Index: \n===================================================================\n--- \n+++ \n@@ -103,9 +103,8 @@\n }\r\n else if($tipe == \"changedata\")\r\n {\r\n     $id  = $_POST['myid'];\r\n-    $group = $_POST['myid'];\r\n     $mysubgroup = $_POST['mydepar'];\r\n     $mysubgroup = $_POST['mydesc'];\r\n     $description = $_POST['mydivision'];\r\n     \r\n"
                },
                {
                    "date": 1629864190326,
                    "content": "Index: \n===================================================================\n--- \n+++ \n@@ -107,9 +107,9 @@\n     $mysubgroup = $_POST['mydepar'];\r\n     $mysubgroup = $_POST['mydesc'];\r\n     $description = $_POST['mydivision'];\r\n     \r\n-    $sql = \"update kategori_subgroup set idkategoriaset = '\".$group.\"', subgroup = '\".$mysubgroup.\"', description = '\".$description.\"' where id = '\".$id.\"'\";\r\n+    $sql = \"update kategori_subgroup set iddivisi = '\".$group.\"', subgroup = '\".$mysubgroup.\"', description = '\".$description.\"' where id = '\".$id.\"'\";\r\n     $res = $conn->query($sql);\r\n     if(($conn -> affected_rows)>0)\r\n     {\r\n         echo \"sukses\";\r\n"
                },
                {
                    "date": 1629864198917,
                    "content": "Index: \n===================================================================\n--- \n+++ \n@@ -104,9 +104,9 @@\n else if($tipe == \"changedata\")\r\n {\r\n     $id  = $_POST['myid'];\r\n     $mysubgroup = $_POST['mydepar'];\r\n-    $mysubgroup = $_POST['mydesc'];\r\n+    $description = $_POST['mydesc'];\r\n     $description = $_POST['mydivision'];\r\n     \r\n     $sql = \"update kategori_subgroup set iddivisi = '\".$group.\"', subgroup = '\".$mysubgroup.\"', description = '\".$description.\"' where id = '\".$id.\"'\";\r\n     $res = $conn->query($sql);\r\n"
                },
                {
                    "date": 1629864205588,
                    "content": "Index: \n===================================================================\n--- \n+++ \n@@ -103,13 +103,13 @@\n }\r\n else if($tipe == \"changedata\")\r\n {\r\n     $id  = $_POST['myid'];\r\n-    $mysubgroup = $_POST['mydepar'];\r\n+    $department = $_POST['mydepar'];\r\n     $description = $_POST['mydesc'];\r\n-    $description = $_POST['mydivision'];\r\n+    $divisi = $_POST['mydivision'];\r\n     \r\n-    $sql = \"update kategori_subgroup set iddivisi = '\".$group.\"', subgroup = '\".$mysubgroup.\"', description = '\".$description.\"' where id = '\".$id.\"'\";\r\n+    $sql = \"update kategori_subgroup set iddivisi = '\".$divisi.\"', subgroup = '\".$mysubgroup.\"', description = '\".$description.\"' where id = '\".$id.\"'\";\r\n     $res = $conn->query($sql);\r\n     if(($conn -> affected_rows)>0)\r\n     {\r\n         echo \"sukses\";\r\n"
                },
                {
                    "date": 1629864212934,
                    "content": "Index: \n===================================================================\n--- \n+++ \n@@ -107,9 +107,9 @@\n     $department = $_POST['mydepar'];\r\n     $description = $_POST['mydesc'];\r\n     $divisi = $_POST['mydivision'];\r\n     \r\n-    $sql = \"update kategori_subgroup set iddivisi = '\".$divisi.\"', subgroup = '\".$mysubgroup.\"', description = '\".$description.\"' where id = '\".$id.\"'\";\r\n+    $sql = \"update kategori_subgroup set iddivisi = '\".$divisi.\"', department = '\".$department.\"', description = '\".$description.\"' where id = '\".$id.\"'\";\r\n     $res = $conn->query($sql);\r\n     if(($conn -> affected_rows)>0)\r\n     {\r\n         echo \"sukses\";\r\n"
                },
                {
                    "date": 1629864278238,
                    "content": "Index: \n===================================================================\n--- \n+++ \n@@ -107,9 +107,9 @@\n     $department = $_POST['mydepar'];\r\n     $description = $_POST['mydesc'];\r\n     $divisi = $_POST['mydivision'];\r\n     \r\n-    $sql = \"update kategori_subgroup set iddivisi = '\".$divisi.\"', department = '\".$department.\"', description = '\".$description.\"' where id = '\".$id.\"'\";\r\n+    $sql = \"update department set iddivisi = '\".$divisi.\"', department = '\".$department.\"', description = '\".$description.\"' where id = '\".$id.\"'\";\r\n     $res = $conn->query($sql);\r\n     if(($conn -> affected_rows)>0)\r\n     {\r\n         echo \"sukses\";\r\n"
                }
            ],
            "date": 1629820726809,
            "name": "Commit-0",
            "content": ""
        }
    ]
}